flametrace/__init__.py
flametrace/core.py
flametrace/main.py
flametrace/perl/flamegraph.pl
tests/__init__.py
tests/test_flametrace.py
flametrace-1.0.1.dist-info/LICENSE
flametrace-1.0.1.dist-info/METADATA
flametrace-1.0.1.dist-info/WHEEL
flametrace-1.0.1.dist-info/entry_points.txt
flametrace-1.0.1.dist-info/top_level.txt
flametrace-1.0.1.dist-info/RECORD
