Metadata-Version: 2.1
Name: flametrace
Version: 1.0.1
Summary: Build flamegraph charts for process trees, based on strace.
Home-page: https://github.com/leifwalsh/flametrace
Author: Leif Walsh
Author-email: leif.walsh@gmail.com
License: BSD 3-Clause License
Platform: UNKNOWN
Classifier: License :: OSI Approved :: BSD License
Classifier: Programming Language :: Python :: 3
Classifier: Development Status :: 4 - Beta
Classifier: Operating System :: POSIX :: Linux
Classifier: Topic :: System :: Benchmark
Requires-Dist: click
